{
  "regime_filter_enabled": "false",
  "regime_filter_mode": "automatic",
  "regime_filter_discovered": "{\"status\": \"ok\", \"strictness\": \"strict\", \"baseline\": {\"count\": 1106, \"win_rate\": 0.5840867992766727, \"expectancy\": 146.17088607594937}, \"subset\": [{\"feature\": \"H1_std_dev_20\", \"direction\": \">\", \"threshold\": 20.177186}, {\"feature\": \"M5_lower_shadow\", \"direction\": \">\", \"threshold\": 1.7}], \"metrics\": {\"count\": 114, \"survival\": 0.1031, \"win_rate\": 0.7105, \"expectancy\": 393.956, \"wr_lift\": 0.1264, \"exp_lift_rel\": 1.6952, \"train_wr\": 0.7253, \"test_wr\": 0.6522, \"score\": 3.4932}}",
  "single_rule_mode_enabled": "true",
  "single_rule_mode_variant": "a",
  "single_rule_mode_discovered": "{\"status\": \"ok\", \"variant\": \"a\", \"trade_count\": 1106, \"chosen\": [{\"feature\": \"D1_volume_change\", \"operator\": \"<\", \"threshold\": 31.238346, \"value\": 31.238346, \"trade_coverage\": 0.9475, \"background_coverage\": null, \"background_coverage_valid\": false, \"tightness\": 0.0183}, {\"feature\": \"H4_bear_power\", \"operator\": \">\", \"threshold\": -116.272441, \"value\": -116.272441, \"trade_coverage\": 0.9494, \"background_coverage\": null, \"background_coverage_valid\": false, \"tightness\": 0.1901}], \"chosen_stats\": {\"joint_coverage\": 0.8816, \"tightness_product\": 0.003479, \"cardinality\": 2}, \"target_coverage\": 0.75}",
  "srm_a_target_coverage": "0.75",
  "srm_a_dedup_correlated": "true",
  "srm_a_winner_selection": "coverage",
  "regime_filter_at_discovery": "true",
  "regime_filter_strictness": "strict",
  "srm_a_per_condition_coverage": "0.90",
  "srm_a_max_cardinality": "8",
  "bot_entry_max_rules": "28",
  "bot_entry_max_depth": "8",
  "prop_firm_id": "leveraged",
  "prop_firm_name": "Get Leveraged",
  "prop_firm_stage": "Evaluation",
  "prop_firm_account": "10000"
}